vegas_params/__init__.py
vegas_params/base.py
vegas_params/collections.py
vegas_params/integration.py
vegas_params/sampling.py
vegas_params/utils.py
vegas_params/vector.py
vegas_params-0.3.1.dist-info/METADATA
vegas_params-0.3.1.dist-info/WHEEL
vegas_params-0.3.1.dist-info/top_level.txt
vegas_params-0.3.1.dist-info/RECORD
