Metadata-Version: 2.4
Name: vegas_params
Version: 0.3.1
Summary: A wrapper for the Vegas integrator
Author-email: Andrey Sheshukov <ash@jinr.ru>
Project-URL: Homepage, https://github.com/RTESolution/vegas_params
Project-URL: Issues, https://github.com/RTESolution/vegas_params/issues
Classifier: Programming Language :: Python :: 3
Classifier: License :: OSI Approved :: MIT License
Classifier: Operating System :: OS Independent
Requires-Python: >=3.8
Requires-Dist: numpy>=1.20
Requires-Dist: vegas>=5.6
Provides-Extra: test
Requires-Dist: pytest>=8; extra == "test"
